MANIFEST.in
setup.py
bricklayer/__init__.py
bricklayer/bricklayer.tac
bricklayer/build_consumer.py
bricklayer/build_container.py
bricklayer/build_info.py
bricklayer/build_options.py
bricklayer/builder.py
bricklayer/builder_deb.py
bricklayer/builder_rpm.py
bricklayer/config.py
bricklayer/git.py
bricklayer/groups.py
bricklayer/model_base.py
bricklayer/projects.py
bricklayer/rest.py
bricklayer.egg-info/PKG-INFO
bricklayer.egg-info/SOURCES.txt
bricklayer.egg-info/dependency_links.txt
bricklayer.egg-info/entry_points.txt
bricklayer.egg-info/top_level.txt
bricklayer/utils/__init__.py
bricklayer/utils/hotqueue.py
bricklayer/utils/dreque/__init__.py
bricklayer/utils/dreque/base.py
bricklayer/utils/dreque/serializer.py
bricklayer/utils/dreque/stats.py
bricklayer/utils/dreque/utils.py
bricklayer/utils/dreque/worker.py
bricklayer/utils/pystache/__init__.py
bricklayer/utils/pystache/template.py
bricklayer/utils/pystache/view.py
etc/bricklayer/bricklayer.ini
etc/bricklayer/gpg.key
pkg_template/rvmrc
pkg_template/deb/README.Debian
pkg_template/deb/README.source
pkg_template/deb/changelog
pkg_template/deb/compat
pkg_template/deb/control
pkg_template/deb/emacsen-install.ex
pkg_template/deb/emacsen-remove.ex
pkg_template/deb/emacsen-startup.ex
pkg_template/deb/init.d.ex
pkg_template/deb/init.d.lsb.ex
pkg_template/deb/manpage.1.ex
pkg_template/deb/manpage.sgml.ex
pkg_template/deb/manpage.xml.ex
pkg_template/deb/menu.ex
pkg_template/deb/package.cron.d.ex
pkg_template/deb/package.default.ex
pkg_template/deb/package.doc-base.EX
pkg_template/deb/postinst.ex
pkg_template/deb/postrm.ex
pkg_template/deb/preinst.ex
pkg_template/deb/prerm.ex
pkg_template/deb/rules
pkg_template/deb/watch.ex
pkg_template/rpm/project.spec
tests/__init__.py
tests/mocker.py
tests/test_builder.py
tests/test_config.py
tests/test_git.py
tests/test_main.py
tests/test_projects.py
web/footer.html
web/header.html
web/index.html
web/css/bootstrap-responsive.css
web/css/bootstrap-responsive.min.css
web/css/bootstrap.css
web/css/bootstrap.min.css
web/css/custom.css
web/css/Aristo/jquery-ui-1.8.7.custom.css
web/css/Aristo/images/bg_fallback.png
web/css/Aristo/images/icon_sprite.png
