Metadata-Version: 1.0
Name: bricklayer
Version: 4.0.23
Summary: A package builder that watch git repositories
Home-page: http://locaweb.github.com
Author: Rodrigo Sampaio Vaz
Author-email: rodrigo.vaz@gmail.com
License: Apache License
Keywords: package builder debian rpm
Platform: UNKNOWN
